main.py
webhooking-0.0.1.dist-info/METADATA
webhooking-0.0.1.dist-info/WHEEL
webhooking-0.0.1.dist-info/top_level.txt
webhooking-0.0.1.dist-info/RECORD
