Metadata-Version: 2.1
Name: webhooking
Version: 0.0.1
Summary: testing with webhooks
